poetry_example_dg/__init__.py
poetry_example_dg/cli.py
poetry_example_dg-0.1.0.dist-info/entry_points.txt
poetry_example_dg-0.1.0.dist-info/WHEEL
poetry_example_dg-0.1.0.dist-info/METADATA
poetry_example_dg-0.1.0.dist-info/RECORD
