Metadata-Version: 2.1
Name: poetry-example-dg
Version: 0.1.0
Summary: 
Home-page: https://github.com/wisemuffin/poetry-example-dg
License: MIT
Keywords: wisemuffin
Author: David Griffiths
Author-email: davidgg777@hotmail.com
Requires-Python: >=3.8,<4.0
Classifier: License :: OSI Approved :: MIT License
Classifier: Programming Language :: Python :: 3
Classifier: Programming Language :: Python :: 3.10
Classifier: Programming Language :: Python :: 3.8
Classifier: Programming Language :: Python :: 3.9
Requires-Dist: click (>=8.1.3,<9.0.0)
Project-URL: Repository, https://github.com/wisemuffin/poetry-example-dg
